[{"__type__":"cc.Prefab","_name":"mailTagNode","data":{"__id__":1}},{"__type__":"cc.Node","_name":"mailTagNode","_components":[{"__type__":"cc.Label","node":{"__id__":1},"_materials":[{"__uuid__":"ecpdLyjvZBwrvm+cedCcQy"}],"_useOriginalSize":false,"_string":"一","_N$string":"一","_lineHeight":60,"_N$horizontalAlign":1,"_N$verticalAlign":1},{"__type__":"cc.Button","node":{"__id__":1},"_N$transition":3,"transition":3,"_N$target":{"__id__":1}},{"__type__":"f34142gIJJJ4YCZvHxJkXfT","node":{"__id__":1},"redPointPrefab":{"__uuid__":"edEgT55g5K0J53Lip+agKe"}}],"_prefab":{"__type__":"cc.PrefabInfo","root":{"__id__":1},"asset":{"__uuid__":"e6Q7cptOtMrY9rDu6ZCKOF"},"fileId":"88lCKeBqtFrL3zLMwiL7ZE"},"_color":{"__type__":"cc.Color","r":102,"g":102,"b":102},"_contentSize":{"__type__":"cc.Size","width":40,"height":75.6},"_trs":{"__type__":"TypedArray","ctor":"Float64Array","array":[0,-86.345,0,0,0,0,1,1,1,1]}}]